trufflepig/__init__.py
trufflepig/_constants.py
trufflepig/client.py
trufflepig/index.py
trufflepig_py-0.1.12.dist-info/LICENSE
trufflepig_py-0.1.12.dist-info/METADATA
trufflepig_py-0.1.12.dist-info/WHEEL
trufflepig_py-0.1.12.dist-info/top_level.txt
trufflepig_py-0.1.12.dist-info/RECORD
