Metadata-Version: 2.1
Name: trufflepig-py
Version: 0.1.12
License-File: LICENSE
Requires-Dist: aiohttp
Requires-Dist: requests
